{
    "DNDConfig": null,
    "_height_": {
        "type": "string",
        "value": "80.17%"
    },
    "_left_": {
        "type": "string",
        "value": "9.111200730860414%"
    },
    "_margin_": [
        0,
        0,
        0,
        0
    ],
    "_orientation_": 6,
    "_padding_": [
        0,
        0,
        0,
        0
    ],
    "_percent_": true,
    "_skin_": "s23f26b31dc441d19c8c3188f8ba5810",
    "_top_": {
        "type": "string",
        "value": "0dp"
    },
    "_width_": {
        "type": "string",
        "value": "27.26%"
    },
    "allboxes": [],
    "autogrowmode": 0,
    "canUpdateUI": true,
    "children": [
        "CopybtnContainer0f1c7efe898c849",
        "CopyLable0hdcd346c3cdc4a"
    ],
    "clipbounds": false,
    "containerweight": 100,
    "enablescrolling": true,
    "id": "chatContainer",
    "info": null,
    "iscustomlayout": false,
    "isvisible": true,
    "kuid": "d7669c03885849c5b0071b3fb0b48e85",
    "layouttype": 4,
    "name": "kony.ui.FlexContainer",
    "parent": "rowthree",
    "pf": "frmHome",
    "retaincontentalignment": false,
    "retainflexpositionproperties": false,
    "retainflowhorizontalalignment": false,
    "snapgridsize": 10,
    "snaptogrid": true,
    "wType": "FlexContainer",
    "widgetalignment": 1
}